.gitignore
MANIFEST.in
setup.py
setuptools_git-0.3.4-py2.6.egg
django_listings.egg-info/PKG-INFO
django_listings.egg-info/SOURCES.txt
django_listings.egg-info/dependency_links.txt
django_listings.egg-info/not-zip-safe
django_listings.egg-info/top_level.txt
listings/__init__.py
listings/__init__.pyc
listings/admin.py
listings/admin.pyc
listings/forms.py
listings/forms.pyc
listings/management.py
listings/management.pyc
listings/models.py
listings/models.pyc
listings/tests.py
listings/tests.pyc
listings/urls.py
listings/urls.pyc
listings/views.py
listings/views.pyc
listings/media/css/listings.css
listings/templates/listings/base.html
listings/templates/listings/listing.html
listings/templates/listings/listing_form.html
listings/templates/listings/listings.html
listings/templates/listings/your_listings.html
listings/templates/listings/tags/add_remove.html
listings/templates/notification/listing_change/notice.html
listings/templates/notification/listing_comment/notice.html
listings/templates/notification/listing_delete/notice.html
listings/templates/notification/listing_done/notice.html
listings/templates/notification/listing_new/notice.html
listings/templates/notification/listing_watch_start/notice.html
listings/templates/notification/listing_watch_stop/notice.html
listings/templatetags/__init__.py
listings/templatetags/__init__.pyc
listings/templatetags/listings_tags.py
listings/templatetags/listings_tags.pyc