Metadata-Version: 1.0
Name: django-listings
Version: 0.1
Summary: django-listings
Home-page: http://github.com/skyl/django-listings
Author: Skylar Saveland
Author-email: skylar.saveland@gmail.com
License: MIT
Keywords: django,pinax,classfieds
Platform: UNKNOWN
Classifier: Programming Language :: Python
Classifier: Topic :: Software Development :: Libraries :: Python Modules
Classifier: Framework :: Django
Classifier: Environment :: Web Environment
